jopen.py
pop_up.py
jira_open-0.1.2.dist-info/entry_points.txt
jira_open-0.1.2.dist-info/LICENSE
jira_open-0.1.2.dist-info/WHEEL
jira_open-0.1.2.dist-info/METADATA
jira_open-0.1.2.dist-info/RECORD
