Metadata-Version: 2.1
Name: jira-open
Version: 0.1.2
Summary: jira open; git check; git bind jira
License: MIT
Author: YunpengZhan
Author-email: 136688059@qq.com
Requires-Python: >=3.7,<4.0
Classifier: License :: OSI Approved :: MIT License
Classifier: Programming Language :: Python :: 3
Classifier: Programming Language :: Python :: 3.10
Classifier: Programming Language :: Python :: 3.7
Classifier: Programming Language :: Python :: 3.8
Classifier: Programming Language :: Python :: 3.9
Requires-Dist: black (>=22.8.0,<23.0.0)
Requires-Dist: requests
Requires-Dist: urwid (>=2.1.2,<3.0.0)
